telegraph/__init__.py
telegraph/api.py
telegraph/exceptions/__init__.py
telegraph/exceptions/telegraph_exception.py
telegraph/helpers/__init__.py
telegraph/helpers/create_account.py
telegraph/helpers/create_page.py
telegraph/helpers/edit_account_info.py
telegraph/helpers/edit_page.py
telegraph/helpers/get_account_info.py
telegraph/helpers/get_page.py
telegraph/helpers/get_page_list.py
telegraph/helpers/get_views.py
telegraph/helpers/revoke_access_token.py
telegraph_uploader-1.0.dist-info/LICENSE
telegraph_uploader-1.0.dist-info/METADATA
telegraph_uploader-1.0.dist-info/WHEEL
telegraph_uploader-1.0.dist-info/top_level.txt
telegraph_uploader-1.0.dist-info/RECORD
