Metadata-Version: 2.1
Name: telegraph_uploader
Version: 1.0
Summary: A Python library for interacting with the Telegraph API
Home-page: https://github.com/lunaticsm/Telegraph
Author: viendi
Author-email: viendii@gmail.com
Classifier: Programming Language :: Python :: 3
Classifier: License :: OSI Approved :: MIT License
Classifier: Operating System :: OS Independent
Requires-Python: >=3.6
License-File: LICENSE
Requires-Dist: requests
